extended_nc_client/__init__.py
extended_nc_client/extended_nc_client.py
extended_nc_client/py.typed
pyncclient_ext-0.1.2.dist-info/LICENSE
pyncclient_ext-0.1.2.dist-info/METADATA
pyncclient_ext-0.1.2.dist-info/WHEEL
pyncclient_ext-0.1.2.dist-info/top_level.txt
pyncclient_ext-0.1.2.dist-info/RECORD
