Metadata-Version: 2.1
Name: pyncclient-ext
Version: 0.1.2
Summary: Python extended Nextcloud Client
Home-page: https://github.com/inab/pyncclient-ext
Author: José M. Fernández <https://orcid.org/0000-0002-4806-5140>
Author-email: jose.m.fernandez@bsc.es
License: MIT
Project-URL: Bug Tracker, https://github.com/inab/pyncclient-ext/issues
Classifier: Programming Language :: Python :: 3
Classifier: Development Status :: 3 - Alpha
Classifier: License :: OSI Approved :: MIT License
Classifier: Operating System :: OS Independent
Requires-Python: >=3.6
License-File: LICENSE
Requires-Dist: pyncclient
Requires-Dist: six
Requires-Dist: typing-extensions
